pyfca/__init__.py
pyfca/implications.py
pyfca-0.3.3.dist-info/LICENSE
pyfca-0.3.3.dist-info/METADATA
pyfca-0.3.3.dist-info/WHEEL
pyfca-0.3.3.dist-info/top_level.txt
pyfca-0.3.3.dist-info/RECORD
