Metadata-Version: 2.1
Name: pyfca
Version: 0.3.3
Summary: pyfca - python formal concept analysis
Home-page: https://github.com/pyfca/pyfca
Author: Roland Puntaier
Author-email: roland.puntaier@gmail.com
License: MIT
Keywords: Documentation
Classifier: Development Status :: 3 - Alpha
Classifier: License :: OSI Approved :: MIT License
Classifier: Operating System :: OS Independent
Classifier: Programming Language :: Python :: 3.6
Classifier: Intended Audience :: Information Technology
License-File: LICENSE
Requires-Dist: svgwrite
Provides-Extra: develop
Requires-Dist: pytest-coverage ; extra == 'develop'
